craigslist/__init__.py
craigslist/cli.py
craigslist/data.py
craigslist/exceptions.py
craigslist/post.py
craigslist/utils.py
craigslist/version.py
craigslist/_search/__init__.py
craigslist/_search/jsonsearch.py
craigslist/_search/regularsearch.py
craigslist/data/areas.json
craigslist/data/arguments.json
craigslist/data/categories.json
craigslist/io/__init__.py
craigslist/io/debug_executor.py
craigslist-0.1.10.dist-info/LICENSE
craigslist-0.1.10.dist-info/METADATA
craigslist-0.1.10.dist-info/WHEEL
craigslist-0.1.10.dist-info/entry_points.txt
craigslist-0.1.10.dist-info/top_level.txt
craigslist-0.1.10.dist-info/RECORD
