Metadata-Version: 2.1
Name: craigslist
Version: 0.1.10
Summary: Python wrapper for craigslist.
Home-page: https://github.com/AlJohri/craigslist
Author: Al Johri
Author-email: al.johri@gmail.com
License: MIT
Platform: UNKNOWN
Classifier: Programming Language :: Python :: 3 :: Only
Classifier: Programming Language :: Python :: 3.6
Classifier: License :: OSI Approved :: MIT License
Requires-Dist: requests
Requires-Dist: cssselect
Requires-Dist: lxml
Requires-Dist: arrow
